mstmap.cpython-37m-x86_64-linux-gnu.so
mstmap-1.1.4.dist-info/LICENSE
mstmap-1.1.4.dist-info/WHEEL
mstmap-1.1.4.dist-info/RECORD
mstmap-1.1.4.dist-info/top_level.txt
mstmap-1.1.4.dist-info/METADATA
