Metadata-Version: 2.2
Name: mstmap
Version: 1.1.4
Summary: A Python library for genetic mapping
Author: Amirsadra Mohseni
Author-email: Amirsadra Mohseni <amohs002@ucr.edu>
License:                                  Apache License
Requires-Python: >=3.7
License-File: LICENSE
Requires-Dist: numpy
Requires-Dist: pandas
Requires-Dist: cython
Requires-Dist: biopython
Requires-Dist: reportlab
Dynamic: author
Dynamic: requires-python
